{
  "ci_gates": [
    "test_anchor_derivation",
    "test_bringup_oracle_complete",
    "test_characterize_timing",
    "test_doc_counts_consistency",
    "test_float_decoders_independent",
    "test_fmt_id_consistency",
    "test_formal_goldens",
    "test_independent_oracle_coverage",
    "test_lns8_independent",
    "test_lut_published_values",
    "test_mutation_guards",
    "test_ondie_coverage_crosscheck",
    "test_pinout_consistency",
    "test_posit8_independent",
    "test_post_silicon_vectors",
    "test_postsilicon_vectors_fresh",
    "test_rom_emitted_golden",
    "test_rom_spec_crosscheck",
    "test_simple_decoders_independent",
    "test_ssot_layout_crosscheck",
    "test_verification_matrix_fresh"
  ],
  "decoders": [
    {
      "bits": 8,
      "codes": 256,
      "decoder": "bcd",
      "formal_golden": "computed",
      "independent_reference": true,
      "mutation_killed": true,
      "post_silicon_vector": true,
      "reference_source": "packed BCD 10*tens+ones"
    },
    {
      "bits": 16,
      "codes": 65536,
      "decoder": "bf16",
      "formal_golden": "definitional",
      "independent_reference": true,
      "mutation_killed": true,
      "post_silicon_vector": true,
      "reference_source": "IEEE bf16 (bits<<16)"
    },
    {
      "bits": 2,
      "codes": 4,
      "decoder": "bitnet",
      "formal_golden": "computed",
      "independent_reference": true,
      "mutation_killed": true,
      "post_silicon_vector": true,
      "reference_source": "BitNet b1.58 ternary (arXiv:2402.17764)"
    },
    {
      "bits": 8,
      "codes": 256,
      "decoder": "e8m0",
      "formal_golden": "computed",
      "independent_reference": true,
      "mutation_killed": true,
      "post_silicon_vector": true,
      "reference_source": "OCP MX scale 2^(e-127)"
    },
    {
      "bits": 4,
      "codes": 16,
      "decoder": "fp4",
      "formal_golden": "LUT",
      "independent_reference": true,
      "mutation_killed": true,
      "post_silicon_vector": true,
      "reference_source": "OCP MX E2M1 (computed)"
    },
    {
      "bits": 6,
      "codes": 64,
      "decoder": "fp6_e2m3",
      "formal_golden": "computed",
      "independent_reference": true,
      "mutation_killed": true,
      "post_silicon_vector": true,
      "reference_source": "OCP MXFP6 E2M3"
    },
    {
      "bits": 6,
      "codes": 64,
      "decoder": "fp6_e3m2",
      "formal_golden": "computed",
      "independent_reference": true,
      "mutation_killed": true,
      "post_silicon_vector": true,
      "reference_source": "OCP MXFP6 E3M2"
    },
    {
      "bits": 8,
      "codes": 256,
      "decoder": "fp8_e4m3_fnuz",
      "formal_golden": "computed",
      "independent_reference": true,
      "mutation_killed": true,
      "post_silicon_vector": true,
      "reference_source": "AMD/Graphcore E4M3FNUZ"
    },
    {
      "bits": 8,
      "codes": 256,
      "decoder": "fp8_e5m2",
      "formal_golden": "computed",
      "independent_reference": true,
      "mutation_killed": true,
      "post_silicon_vector": true,
      "reference_source": "OCP OFP8 E5M2 (arXiv:2209.05433)"
    },
    {
      "bits": 4,
      "codes": 16,
      "decoder": "int4",
      "formal_golden": "computed",
      "independent_reference": true,
      "mutation_killed": true,
      "post_silicon_vector": true,
      "reference_source": "two's complement"
    },
    {
      "bits": 8,
      "codes": 256,
      "decoder": "int8",
      "formal_golden": "computed",
      "independent_reference": true,
      "mutation_killed": true,
      "post_silicon_vector": true,
      "reference_source": "two's complement"
    },
    {
      "bits": 8,
      "codes": 256,
      "decoder": "lns8",
      "formal_golden": "LUT",
      "independent_reference": true,
      "mutation_killed": true,
      "post_silicon_vector": true,
      "reference_source": "antilog round(256*2^(i/16))"
    },
    {
      "bits": 8,
      "codes": 256,
      "decoder": "mxfp8_e4m3",
      "formal_golden": "computed",
      "independent_reference": true,
      "mutation_killed": true,
      "post_silicon_vector": true,
      "reference_source": "OCP E4M3 (no Inf, 2 NaN)"
    },
    {
      "bits": 8,
      "codes": 256,
      "decoder": "mxint8",
      "formal_golden": "computed",
      "independent_reference": true,
      "mutation_killed": true,
      "post_silicon_vector": true,
      "reference_source": "OCP MX int * 2^-6"
    },
    {
      "bits": 4,
      "codes": 16,
      "decoder": "nf4",
      "formal_golden": "LUT",
      "independent_reference": true,
      "mutation_killed": true,
      "post_silicon_vector": true,
      "reference_source": "QLoRA NF4 quantiles (arXiv:2305.14314)"
    },
    {
      "bits": 8,
      "codes": 256,
      "decoder": "posit8",
      "formal_golden": "LUT",
      "independent_reference": true,
      "mutation_killed": true,
      "post_silicon_vector": true,
      "reference_source": "Posit Standard 2022 + johndcook table"
    },
    {
      "bits": 19,
      "codes": 524288,
      "decoder": "tf32",
      "formal_golden": "definitional",
      "independent_reference": true,
      "mutation_killed": true,
      "post_silicon_vector": true,
      "reference_source": "NVIDIA TF32 field repack"
    }
  ],
  "schema": "corona-verification/1",
  "summary": {
    "ci_gates": 21,
    "decoders": 17,
    "formal_harnesses": 17,
    "independent_references": 17,
    "mutation_killed": 17,
    "post_silicon_coverage": 17,
    "total_codes": 592308
  }
}
